{"ocid":"ocds-vesric-YHL5-20190719155348","id":"ocds-vesric-YHL5-20190719155348-QT190000000032075","date":"2019-07-19T15:53:48+08:00","language":"ms","tag":["tender","award"],"initiationType":"tender","parties":[{"id":"357-02133120","name":"VIRALINK CORPORATION SDN BHD","roles":["tenderer"]},{"id":"357-02055157","name":"PK GEMILANG","roles":["tenderer"]},{"id":"357-02177326","name":"KALIBER ENGINEERING WORKS","roles":["tenderer"]},{"id":"357-02234006","name":"QINOS MARKETING SDN. BHD.","roles":["tenderer","supplier"]},{"id":"357-02064821","name":"KHALIS PROMINANCE","roles":["tenderer"]},{"id":"357-02167258","name":"NJ GLOBAL SERVICES","roles":["tenderer"]},{"id":"357-02228416","name":"ALTA VISTA SOLUTION","roles":["tenderer"]},{"id":"139","name":"KEMENTERIAN TENAGA, SAINS, TEKNOLOGI, ALAM SEKITAR DAN PERUBAHAN IKLIM","roles":["buyer"]},{"id":"38","name":"KUMPULAN PTJ KEMENTERIAN TENAGA, SAINS, TEKNOLOGI ALAM SEKITAR DAN PERUBAHAN IKLIM","roles":["procuringEntity"]}],"buyer":{"id":"38","name":"KUMPULAN PTJ KEMENTERIAN TENAGA, SAINS, TEKNOLOGI ALAM SEKITAR DAN PERUBAHAN IKLIM"},"tender":{"id":"ocds-vesric-YHL5-20190719155348-QT190000000032075-tender","title":"PERKHIDMATAN PEMBAHARUAN LESEN SISTEM PENGALIHUDARAAN SETEMPAT (LEV) DI AGENSI NUKLEAR MALAYSIA - SH.13\/2019","status":"complete","procurementMethod":"limited","tenderPeriod":{"startDate":"2019-07-19T15:53:48+08:00","endDate":"2019-07-19T15:53:48+08:00"},"numberOfTenderers":7,"tenderers":[{"id":"357-02133120","name":"VIRALINK CORPORATION SDN BHD"},{"id":"357-02055157","name":"PK GEMILANG"},{"id":"357-02177326","name":"KALIBER ENGINEERING WORKS"},{"id":"357-02234006","name":"QINOS MARKETING SDN. BHD."},{"id":"357-02064821","name":"KHALIS PROMINANCE"},{"id":"357-02167258","name":"NJ GLOBAL SERVICES"},{"id":"357-02228416","name":"ALTA VISTA SOLUTION"}]},"awards":[{"id":"ocds-vesric-YHL5-20190719155348-QT190000000032075-award","title":"PERKHIDMATAN PEMBAHARUAN LESEN SISTEM PENGALIHUDARAAN SETEMPAT (LEV) DI AGENSI NUKLEAR MALAYSIA - SH.13\/2019","status":"active","value":{"amount":"42280.00","currency":"MYR"},"suppliers":[{"id":"357-02234006","name":"QINOS MARKETING SDN. BHD."}]}]}