{"ocid":"ocds-vesric-FPRB-20190719155034","id":"ocds-vesric-FPRB-20190719155034-QT190000000046707","date":"2019-07-19T15:50:34+08:00","language":"ms","tag":["tender","award"],"initiationType":"tender","parties":[{"id":"357-00028844","name":"FORMIS NETWORK SERVICES SDN BHD","roles":["tenderer","supplier"]},{"id":"146","name":"KEMENTERIAN DALAM NEGERI","roles":["buyer"]},{"id":"52","name":"KUMPULAN PTJ KEMENTERIAN DALAM NEGERI","roles":["procuringEntity"]}],"buyer":{"id":"52","name":"KUMPULAN PTJ KEMENTERIAN DALAM NEGERI"},"tender":{"id":"ocds-vesric-FPRB-20190719155034-QT190000000046707-tender","title":"PERKHIDMATAN SEWAAN SISTEM RAKAMAN INKUES BAGI KEGUNAAN SURUHANJAYA SIASATAN DIRAJA (RCI) OLEH KEMENTERIAN DALAM NEGERI","status":"complete","procurementMethod":"limited","tenderPeriod":{"startDate":"2019-07-19T15:50:34+08:00","endDate":"2019-07-19T15:50:34+08:00"},"numberOfTenderers":1,"tenderers":[{"id":"357-00028844","name":"FORMIS NETWORK SERVICES SDN BHD"}]},"awards":[{"id":"ocds-vesric-FPRB-20190719155034-QT190000000046707-award","title":"PERKHIDMATAN SEWAAN SISTEM RAKAMAN INKUES BAGI KEGUNAAN SURUHANJAYA SIASATAN DIRAJA (RCI) OLEH KEMENTERIAN DALAM NEGERI","status":"active","value":{"amount":"49950.00","currency":"MYR"},"suppliers":[{"id":"357-00028844","name":"FORMIS NETWORK SERVICES SDN BHD"}]}]}