{"uri":"https:\/\/cartelogy.data.gov.my\/ocds\/2019\/ocds-vesric-N3G9-20190719155827.json","version":"1.1","publishedDate":"2019-07-19T15:58:27+08:00","releases":[{"ocid":"ocds-vesric-N3G9-20190719155827","id":"ocds-vesric-N3G9-20190719155827-QT190000000042972","date":"2019-07-19T15:58:27+08:00","language":"ms","tag":["tender","award"],"initiationType":"tender","parties":[{"id":"357-0002303269","name":"FZR TRADING RESOURCES","roles":["tenderer"]},{"id":"357-02171262","name":"QAZAI SALE AND SERVICES","roles":["tenderer"]},{"id":"357-02252565","name":"ANNEX COMPUTER SALES & SERVICE SDN. BHD.","roles":["tenderer"]},{"id":"357-02252599","name":"MV OCEAN STAR TRADING","roles":["tenderer"]},{"id":"357-02208954","name":"TEGUH HATI ENTERPRISE","roles":["tenderer"]},{"id":"357-02229398","name":"SMART SOLARIS SDN BHD","roles":["tenderer"]},{"id":"357-0002296545","name":"REZKI MUMTAZ RESOURCES","roles":["tenderer"]},{"id":"357-02097345","name":"ART MULTIMEDIA TECHNOLOGY","roles":["tenderer"]},{"id":"357-02099625","name":"FYZAD ENTERPRISE","roles":["tenderer"]},{"id":"357-0002286062","name":"OKITA TRADING","roles":["tenderer"]},{"id":"357-02240272","name":"MAZ SUPPLY","roles":["tenderer"]},{"id":"357-02257109","name":"SNG LEGACY TRADING","roles":["tenderer"]},{"id":"357-02058984","name":"AURA NIAGA","roles":["tenderer"]},{"id":"357-02114238","name":"ARENA STABIL SDN. BHD","roles":["tenderer"]},{"id":"357-02061814","name":"BEKALAN BAKTI ENTERPRISE","roles":["tenderer"]},{"id":"357-02015598","name":"BURHANI STATIONERS","roles":["tenderer","supplier"]},{"id":"357-02214685","name":"JCT SMART SUPPLY","roles":["tenderer"]},{"id":"357-02193865","name":"FASTSUPPORT","roles":["tenderer"]},{"id":"357-02116144","name":"PRIESMA TRADING","roles":["tenderer"]},{"id":"357-0002298706","name":"NEXTCOM OFFICE SUPPLIES","roles":["tenderer"]},{"id":"357-02217271","name":"MHL MEDIA SUPPLY","roles":["tenderer"]},{"id":"357-02179039","name":"MEGAH BERJAYA TRADING & SERVICES","roles":["tenderer"]},{"id":"357-02095719","name":"IWANI NIAGA","roles":["tenderer"]},{"id":"357-02201738","name":"NADZ COM ENTERPRISE","roles":["tenderer"]},{"id":"357-00042071","name":"COWELL RESOURCES","roles":["tenderer"]},{"id":"121","name":"KEMENTERIAN BELIA DAN SUKAN","roles":["buyer"]},{"id":"46","name":"KUMPULAN PTJ KEMENTERIAN BELIA DAN SUKAN","roles":["procuringEntity"]}],"buyer":{"id":"46","name":"KUMPULAN PTJ KEMENTERIAN BELIA DAN SUKAN"},"tender":{"id":"ocds-vesric-N3G9-20190719155827-QT190000000042972-tender","title":"SEBUT HARGA MEMBEKAL ALAT TULIS DAN PERALATAN PEJABAT SIRI 1\/2019 DI IKTBN CHEMBONG","status":"complete","procurementMethod":"limited","tenderPeriod":{"startDate":"2019-07-19T15:58:27+08:00","endDate":"2019-07-19T15:58:27+08:00"},"numberOfTenderers":25,"tenderers":[{"id":"357-0002303269","name":"FZR TRADING RESOURCES"},{"id":"357-02171262","name":"QAZAI SALE AND SERVICES"},{"id":"357-02252565","name":"ANNEX COMPUTER SALES & SERVICE SDN. BHD."},{"id":"357-02252599","name":"MV OCEAN STAR TRADING"},{"id":"357-02208954","name":"TEGUH HATI ENTERPRISE"},{"id":"357-02229398","name":"SMART SOLARIS SDN BHD"},{"id":"357-0002296545","name":"REZKI MUMTAZ RESOURCES"},{"id":"357-02097345","name":"ART MULTIMEDIA TECHNOLOGY"},{"id":"357-02099625","name":"FYZAD ENTERPRISE"},{"id":"357-0002286062","name":"OKITA TRADING"},{"id":"357-02240272","name":"MAZ SUPPLY"},{"id":"357-02257109","name":"SNG LEGACY TRADING"},{"id":"357-02058984","name":"AURA NIAGA"},{"id":"357-02114238","name":"ARENA STABIL SDN. BHD"},{"id":"357-02061814","name":"BEKALAN BAKTI ENTERPRISE"},{"id":"357-02015598","name":"BURHANI STATIONERS"},{"id":"357-02214685","name":"JCT SMART SUPPLY"},{"id":"357-02193865","name":"FASTSUPPORT"},{"id":"357-02116144","name":"PRIESMA TRADING"},{"id":"357-0002298706","name":"NEXTCOM OFFICE SUPPLIES"},{"id":"357-02217271","name":"MHL MEDIA SUPPLY"},{"id":"357-02179039","name":"MEGAH BERJAYA TRADING & SERVICES"},{"id":"357-02095719","name":"IWANI NIAGA"},{"id":"357-02201738","name":"NADZ COM ENTERPRISE"},{"id":"357-00042071","name":"COWELL RESOURCES"}]},"awards":[{"id":"ocds-vesric-N3G9-20190719155827-QT190000000042972-award","title":"SEBUT HARGA MEMBEKAL ALAT TULIS DAN PERALATAN PEJABAT SIRI 1\/2019 DI IKTBN CHEMBONG","status":"active","value":{"amount":"25652.00","currency":"MYR"},"suppliers":[{"id":"357-02015598","name":"BURHANI STATIONERS"}]}]}],"publisher":{"name":"MALAYSIAN ADMINISTRATIVE MODERNISATION AND MANAGEMENT PLANNING UNIT","uri":"https:\/\/www.mampu.gov.my"}}