{"uri":"https:\/\/cartelogy.data.gov.my\/ocds\/2019\/ocds-vesric-RXFL-20190719154856.json","version":"1.1","publishedDate":"2019-07-19T15:48:56+08:00","releases":[{"ocid":"ocds-vesric-RXFL-20190719154856","id":"ocds-vesric-RXFL-20190719154856-QT190000000033477","date":"2019-07-19T15:48:56+08:00","language":"ms","tag":["tender","award"],"initiationType":"tender","parties":[{"id":"357-02217046","name":"NUR ELIYA ENTERPRISE","roles":["tenderer"]},{"id":"357-02118352","name":"KORIRDOR JAYA TRADING","roles":["tenderer"]},{"id":"357-02217680","name":"DATA DELTA ENTERPRISE","roles":["tenderer"]},{"id":"357-02224742","name":"AMZ SEPAKAT GLOBAL SDN. BHD.","roles":["tenderer"]},{"id":"357-00037499","name":"TIMUR JANITOR SDN. BHD.","roles":["tenderer"]},{"id":"357-02267864","name":"ANMJ 92 ENTERPRISE","roles":["tenderer"]},{"id":"357-02258486","name":"ADIL URUS ENTERPRISE","roles":["tenderer"]},{"id":"357-02226136","name":"PERNIAGAAN NGAH EMBONG SDN. BHD.","roles":["tenderer"]},{"id":"357-02091547","name":"MKH ENGINEERING AND SERVICES","roles":["tenderer"]},{"id":"357-0002285971","name":"AQUA BLAST SERVICES & SUPPLIES","roles":["tenderer"]},{"id":"357-02125077","name":"NUC TEGUH ENTERPRISE","roles":["tenderer"]},{"id":"357-02040066","name":"ADNAN BIN YAACOB","roles":["tenderer"]},{"id":"357-02252790","name":"AMIRDIN JAYA ENTERPRISE","roles":["tenderer"]},{"id":"357-02048495","name":"WAWASAN MJ ENTERPRISE","roles":["tenderer"]},{"id":"357-02218021","name":"AZA VENTURE SDN. BHD.","roles":["tenderer"]},{"id":"357-02283317","name":"MFH GENIUS RESOURCES","roles":["tenderer"]},{"id":"357-02268230","name":"QALIF TEGUH ENTERPRISE","roles":["tenderer"]},{"id":"357-02132019","name":"NAZIM HAJAR ENTERPRISE","roles":["tenderer"]},{"id":"357-02151115","name":"M TAM ENTERPRISE","roles":["tenderer"]},{"id":"357-02200953","name":"MYZAM MULTI TRADING AND SERVICES","roles":["tenderer"]},{"id":"357-02226916","name":"PETITI JAYA ENTERPRISE","roles":["tenderer"]},{"id":"357-00021129","name":"MAHIDIN BIN DOLLAH","roles":["tenderer"]},{"id":"357-02215424","name":"INPRO RESOURCES","roles":["tenderer"]},{"id":"357-02221479","name":"MOLEK URUS ENTERPRISE","roles":["tenderer"]},{"id":"357-0002290762","name":"NFL RINTIS ENTERPRISE","roles":["tenderer"]},{"id":"357-02168231","name":"PRIMA TIMUR ENTERPRISE","roles":["tenderer"]},{"id":"357-02284061","name":"WAN ROSNARIAH BINTI WAN MOHAMAD","roles":["tenderer"]},{"id":"357-02181571","name":"HYNASZ TECHNOLOGY","roles":["tenderer"]},{"id":"357-02217922","name":"PNQ GOLD SDN.BHD.","roles":["tenderer"]},{"id":"357-02131924","name":"SYIRA MAJU ENTERPRISE","roles":["tenderer","supplier"]},{"id":"357-02203797","name":"PURNAMA TEGAK MULTI TRADING AND SERVICES","roles":["tenderer"]},{"id":"357-02099355","name":"KEY ONE RESOURCES SDN BHD","roles":["tenderer"]},{"id":"357-02033306","name":"KAB ADIL ENTERPRISE","roles":["tenderer"]},{"id":"357-02241541","name":"ZIECON ENERGY RESOURCES","roles":["tenderer"]},{"id":"144","name":"KEMENTERIAN PERDAGANGAN DALAM NEGERI DAN HAL EHWAL PENGGUNA","roles":["buyer"]},{"id":"34","name":"KUMPULAN PTJ KEMENTERIAN PERDAGANGAN DALAM NEGERI, KOPERASI DAN KEPENGGUNAAN","roles":["procuringEntity"]}],"buyer":{"id":"34","name":"KUMPULAN PTJ KEMENTERIAN PERDAGANGAN DALAM NEGERI, KOPERASI DAN KEPENGGUNAAN"},"tender":{"id":"ocds-vesric-RXFL-20190719154856-QT190000000033477-tender","title":"PERKHIDMATAN PEMBERSIHAN PEJABAT KEMENTERIAN PERDAGANGAN DALAM NEGERI DAN HAL EHWAL PENGGUNA (KPDNHEP) NEGERI TERENGGANU DAN CAWANGAN ","status":"complete","procurementMethod":"limited","tenderPeriod":{"startDate":"2019-07-19T15:48:56+08:00","endDate":"2019-07-19T15:48:56+08:00"},"numberOfTenderers":34,"tenderers":[{"id":"357-02217046","name":"NUR ELIYA ENTERPRISE"},{"id":"357-02118352","name":"KORIRDOR JAYA TRADING"},{"id":"357-02217680","name":"DATA DELTA ENTERPRISE"},{"id":"357-02224742","name":"AMZ SEPAKAT GLOBAL SDN. BHD."},{"id":"357-00037499","name":"TIMUR JANITOR SDN. BHD."},{"id":"357-02267864","name":"ANMJ 92 ENTERPRISE"},{"id":"357-02258486","name":"ADIL URUS ENTERPRISE"},{"id":"357-02226136","name":"PERNIAGAAN NGAH EMBONG SDN. BHD."},{"id":"357-02091547","name":"MKH ENGINEERING AND SERVICES"},{"id":"357-0002285971","name":"AQUA BLAST SERVICES & SUPPLIES"},{"id":"357-02125077","name":"NUC TEGUH ENTERPRISE"},{"id":"357-02040066","name":"ADNAN BIN YAACOB"},{"id":"357-02252790","name":"AMIRDIN JAYA ENTERPRISE"},{"id":"357-02048495","name":"WAWASAN MJ ENTERPRISE"},{"id":"357-02218021","name":"AZA VENTURE SDN. BHD."},{"id":"357-02283317","name":"MFH GENIUS RESOURCES"},{"id":"357-02268230","name":"QALIF TEGUH ENTERPRISE"},{"id":"357-02132019","name":"NAZIM HAJAR ENTERPRISE"},{"id":"357-02151115","name":"M TAM ENTERPRISE"},{"id":"357-02200953","name":"MYZAM MULTI TRADING AND SERVICES"},{"id":"357-02226916","name":"PETITI JAYA ENTERPRISE"},{"id":"357-00021129","name":"MAHIDIN BIN DOLLAH"},{"id":"357-02215424","name":"INPRO RESOURCES"},{"id":"357-02221479","name":"MOLEK URUS ENTERPRISE"},{"id":"357-0002290762","name":"NFL RINTIS ENTERPRISE"},{"id":"357-02168231","name":"PRIMA TIMUR ENTERPRISE"},{"id":"357-02284061","name":"WAN ROSNARIAH BINTI WAN MOHAMAD"},{"id":"357-02181571","name":"HYNASZ TECHNOLOGY"},{"id":"357-02217922","name":"PNQ GOLD SDN.BHD."},{"id":"357-02131924","name":"SYIRA MAJU ENTERPRISE"},{"id":"357-02203797","name":"PURNAMA TEGAK MULTI TRADING AND SERVICES"},{"id":"357-02099355","name":"KEY ONE RESOURCES SDN BHD"},{"id":"357-02033306","name":"KAB ADIL ENTERPRISE"},{"id":"357-02241541","name":"ZIECON ENERGY RESOURCES"}]},"awards":[{"id":"ocds-vesric-RXFL-20190719154856-QT190000000033477-award","title":"PERKHIDMATAN PEMBERSIHAN PEJABAT KEMENTERIAN PERDAGANGAN DALAM NEGERI DAN HAL EHWAL PENGGUNA (KPDNHEP) NEGERI TERENGGANU DAN CAWANGAN ","status":"active","value":{"amount":"238320.00","currency":"MYR"},"suppliers":[{"id":"357-02131924","name":"SYIRA MAJU ENTERPRISE"}]}]}],"publisher":{"name":"MALAYSIAN ADMINISTRATIVE MODERNISATION AND MANAGEMENT PLANNING UNIT","uri":"https:\/\/www.mampu.gov.my"}}