{"ocid":"ocds-vesric-OXVV-20190719154922","id":"ocds-vesric-OXVV-20190719154922-QT190000000051364","date":"2019-07-19T15:49:22+08:00","language":"ms","tag":["tender","award"],"initiationType":"tender","parties":[{"id":"357-02199471","name":"CENDANA BARU ENTERPRISE","roles":["tenderer"]},{"id":"357-00046150","name":"KEJURUTERAAN TENAGA SEPADU","roles":["tenderer"]},{"id":"357-02104261","name":"PERMAI AU ENTERPRISE","roles":["tenderer","supplier"]},{"id":"357-02029191","name":"SRI KENALI AIRCOND SERVICE","roles":["tenderer"]},{"id":"357-02010350","name":"AIRESTEC SDN BHD","roles":["tenderer"]},{"id":"357-0002305204","name":"ELITE GREEN TECHNOLOGY SDN BHD","roles":["tenderer"]},{"id":"117","name":"KEMENTERIAN PERTAHANAN","roles":["buyer"]},{"id":"51","name":"KUMPULAN PTJ KEMENTERIAN PERTAHANAN","roles":["procuringEntity"]}],"buyer":{"id":"51","name":"KUMPULAN PTJ KEMENTERIAN PERTAHANAN"},"tender":{"id":"ocds-vesric-OXVV-20190719154922-QT190000000051364-tender","title":"PEROLEHAN SENGGARAAN KELENGKAPAN ALAT PENGHAWA DINGIN DI BAHAGIAN STAF PERISIKAN PERTAHANAN","status":"complete","procurementMethod":"limited","tenderPeriod":{"startDate":"2019-07-19T15:49:22+08:00","endDate":"2019-07-19T15:49:22+08:00"},"numberOfTenderers":6,"tenderers":[{"id":"357-02199471","name":"CENDANA BARU ENTERPRISE"},{"id":"357-00046150","name":"KEJURUTERAAN TENAGA SEPADU"},{"id":"357-02104261","name":"PERMAI AU ENTERPRISE"},{"id":"357-02029191","name":"SRI KENALI AIRCOND SERVICE"},{"id":"357-02010350","name":"AIRESTEC SDN BHD"},{"id":"357-0002305204","name":"ELITE GREEN TECHNOLOGY SDN BHD"}]},"awards":[{"id":"ocds-vesric-OXVV-20190719154922-QT190000000051364-award","title":"PEROLEHAN SENGGARAAN KELENGKAPAN ALAT PENGHAWA DINGIN DI BAHAGIAN STAF PERISIKAN PERTAHANAN","status":"active","value":{"amount":"174984.00","currency":"MYR"},"suppliers":[{"id":"357-02104261","name":"PERMAI AU ENTERPRISE"}]}]}