{"uri":"https:\/\/cartelogy.data.gov.my\/ocds\/2019\/ocds-vesric-UQUE-20190719155033.json","version":"1.1","publishedDate":"2019-07-19T15:50:33+08:00","releases":[{"ocid":"ocds-vesric-UQUE-20190719155033","id":"ocds-vesric-UQUE-20190719155033-QT190000000045984","date":"2019-07-19T15:50:33+08:00","language":"ms","tag":["tender","award"],"initiationType":"tender","parties":[{"id":"357-02099889","name":"TRP TECHNOLOGIES (M) SDN BHD","roles":["tenderer"]},{"id":"357-01001169","name":"MEDIGENE SDN BHD","roles":["tenderer"]},{"id":"357-02055526","name":"FISHER SCIENTIFIC (M) SDN. BHD.","roles":["tenderer"]},{"id":"357-00041892","name":"PREMIER DIAGNOSTICS SDN BHD","roles":["tenderer"]},{"id":"357-00015706","name":"SYARIKAT PUSTAKA ELIT","roles":["tenderer"]},{"id":"357-02031071","name":"IT TECH RESEARCH (M) SDN BHD","roles":["tenderer"]},{"id":"357-02011839","name":"CERENKOV SCIENTIFIC SDN. BHD.","roles":["tenderer"]},{"id":"357-02233945","name":"VNK SUPPLY & SERVICES","roles":["tenderer","supplier"]},{"id":"357-00015902","name":"PERMULA SDN. BHD.","roles":["tenderer"]},{"id":"357-00001926","name":"SURIA PEMBEKAL UMUM SDN. BHD.","roles":["tenderer"]},{"id":"357-02011122","name":"ANALISA RESOURCES (M) SDN BHD","roles":["tenderer"]},{"id":"357-02099889","name":"TRP TECHNOLOGIES (M) SDN BHD","roles":["tenderer"]},{"id":"357-01001169","name":"MEDIGENE SDN BHD","roles":["tenderer"]},{"id":"357-02055526","name":"FISHER SCIENTIFIC (M) SDN. BHD.","roles":["tenderer"]},{"id":"357-00041892","name":"PREMIER DIAGNOSTICS SDN BHD","roles":["tenderer"]},{"id":"357-00015706","name":"SYARIKAT PUSTAKA ELIT","roles":["tenderer"]},{"id":"357-02031071","name":"IT TECH RESEARCH (M) SDN BHD","roles":["tenderer"]},{"id":"357-02011839","name":"CERENKOV SCIENTIFIC SDN. BHD.","roles":["tenderer"]},{"id":"357-02233945","name":"VNK SUPPLY & SERVICES","roles":["tenderer","supplier"]},{"id":"357-00015902","name":"PERMULA SDN. BHD.","roles":["tenderer"]},{"id":"357-00001926","name":"SURIA PEMBEKAL UMUM SDN. BHD.","roles":["tenderer"]},{"id":"357-02011122","name":"ANALISA RESOURCES (M) SDN BHD","roles":["tenderer"]},{"id":"139","name":"KEMENTERIAN TENAGA, SAINS, TEKNOLOGI, ALAM SEKITAR DAN PERUBAHAN IKLIM","roles":["buyer"]},{"id":"38","name":"KUMPULAN PTJ KEMENTERIAN TENAGA, SAINS, TEKNOLOGI ALAM SEKITAR DAN PERUBAHAN IKLIM","roles":["procuringEntity"]}],"buyer":{"id":"38","name":"KUMPULAN PTJ KEMENTERIAN TENAGA, SAINS, TEKNOLOGI ALAM SEKITAR DAN PERUBAHAN IKLIM"},"tender":{"id":"ocds-vesric-UQUE-20190719155033-QT190000000045984-tender","title":"SEBUTHARGA BEKALAN CONSUMABLE BAGI SEKSYEN BIOLOGI KE JABATAN KIMIA MALAYSIA NEGERI JOHOR UNTUK TAHUN 2019","status":"complete","procurementMethod":"limited","tenderPeriod":{"startDate":"2019-07-19T15:50:33+08:00","endDate":"2019-07-19T15:50:33+08:00"},"numberOfTenderers":22,"tenderers":[{"id":"357-02099889","name":"TRP TECHNOLOGIES (M) SDN BHD"},{"id":"357-01001169","name":"MEDIGENE SDN BHD"},{"id":"357-02055526","name":"FISHER SCIENTIFIC (M) SDN. BHD."},{"id":"357-00041892","name":"PREMIER DIAGNOSTICS SDN BHD"},{"id":"357-00015706","name":"SYARIKAT PUSTAKA ELIT"},{"id":"357-02031071","name":"IT TECH RESEARCH (M) SDN BHD"},{"id":"357-02011839","name":"CERENKOV SCIENTIFIC SDN. BHD."},{"id":"357-02233945","name":"VNK SUPPLY & SERVICES"},{"id":"357-00015902","name":"PERMULA SDN. BHD."},{"id":"357-00001926","name":"SURIA PEMBEKAL UMUM SDN. BHD."},{"id":"357-02011122","name":"ANALISA RESOURCES (M) SDN BHD"},{"id":"357-02099889","name":"TRP TECHNOLOGIES (M) SDN BHD"},{"id":"357-01001169","name":"MEDIGENE SDN BHD"},{"id":"357-02055526","name":"FISHER SCIENTIFIC (M) SDN. BHD."},{"id":"357-00041892","name":"PREMIER DIAGNOSTICS SDN BHD"},{"id":"357-00015706","name":"SYARIKAT PUSTAKA ELIT"},{"id":"357-02031071","name":"IT TECH RESEARCH (M) SDN BHD"},{"id":"357-02011839","name":"CERENKOV SCIENTIFIC SDN. BHD."},{"id":"357-02233945","name":"VNK SUPPLY & SERVICES"},{"id":"357-00015902","name":"PERMULA SDN. BHD."},{"id":"357-00001926","name":"SURIA PEMBEKAL UMUM SDN. BHD."},{"id":"357-02011122","name":"ANALISA RESOURCES (M) SDN BHD"}]},"awards":[{"id":"ocds-vesric-UQUE-20190719155033-QT190000000045984-award","title":"SEBUTHARGA BEKALAN CONSUMABLE BAGI SEKSYEN BIOLOGI KE JABATAN KIMIA MALAYSIA NEGERI JOHOR UNTUK TAHUN 2019","status":"active","value":{"amount":"5200.00","currency":"MYR"},"suppliers":[{"id":"357-02233945","name":"VNK SUPPLY & SERVICES"}]}]}],"publisher":{"name":"MALAYSIAN ADMINISTRATIVE MODERNISATION AND MANAGEMENT PLANNING UNIT","uri":"https:\/\/www.mampu.gov.my"}}