{"uri":"https:\/\/cartelogy.data.gov.my\/ocds\/2019\/ocds-vesric-0U1D-20190719153901.json","version":"1.1","publishedDate":"2019-07-19T15:39:01+08:00","releases":[{"ocid":"ocds-vesric-0U1D-20190719153901","id":"ocds-vesric-0U1D-20190719153901-QT190000000046835","date":"2019-07-19T15:39:01+08:00","language":"ms","tag":["tender","award"],"initiationType":"tender","parties":[{"id":"357-0002287106","name":"QY BERKAT RAIJ RESOURCES","roles":["tenderer","supplier"]},{"id":"357-02212963","name":"THERA KIRA ENTERPRISE","roles":["tenderer"]},{"id":"357-0002286240","name":"F.A.M MAKEUP ACADEMY","roles":["tenderer"]},{"id":"140","name":"KEMENTERIAN PEMBANGUNAN LUAR BANDAR","roles":["buyer"]},{"id":"31","name":"KUMPULAN PTJ KEMENTERIAN PEMBANGUNAN LUAR BANDAR","roles":["procuringEntity"]}],"buyer":{"id":"31","name":"KUMPULAN PTJ KEMENTERIAN PEMBANGUNAN LUAR BANDAR"},"tender":{"id":"ocds-vesric-0U1D-20190719153901-QT190000000046835-tender","title":"MEMBEKAL DAN MENGHANTAR PERALATAN DANDANAN DIRI PROGRAM QUICK WIN SOLEKAN PROFESIONAL KEMAS TAHUN 2019","status":"complete","procurementMethod":"limited","tenderPeriod":{"startDate":"2019-07-19T15:39:01+08:00","endDate":"2019-07-19T15:39:01+08:00"},"numberOfTenderers":3,"tenderers":[{"id":"357-0002287106","name":"QY BERKAT RAIJ RESOURCES"},{"id":"357-02212963","name":"THERA KIRA ENTERPRISE"},{"id":"357-0002286240","name":"F.A.M MAKEUP ACADEMY"}]},"awards":[{"id":"ocds-vesric-0U1D-20190719153901-QT190000000046835-award","title":"MEMBEKAL DAN MENGHANTAR PERALATAN DANDANAN DIRI PROGRAM QUICK WIN SOLEKAN PROFESIONAL KEMAS TAHUN 2019","status":"active","value":{"amount":"26600.00","currency":"MYR"},"suppliers":[{"id":"357-0002287106","name":"QY BERKAT RAIJ RESOURCES"}]}]}],"publisher":{"name":"MALAYSIAN ADMINISTRATIVE MODERNISATION AND MANAGEMENT PLANNING UNIT","uri":"https:\/\/www.mampu.gov.my"}}