{"ocid":"ocds-vesric-2IN6-20190719154440","id":"ocds-vesric-2IN6-20190719154440-QT190000000034859","date":"2019-07-19T15:44:40+08:00","language":"ms","tag":["tender","award"],"initiationType":"tender","parties":[{"id":"357-20025389","name":"BINTAFA HOLDING","roles":["tenderer","supplier"]},{"id":"357-20020890","name":"EMMA PUNCAK JAYA ENTERPRISE","roles":["tenderer"]},{"id":"357-20031897","name":"ZAIKON MEWAH ENTERPRISE","roles":["tenderer"]},{"id":"357-20031079","name":"G. GENERATION AGENCY","roles":["tenderer"]},{"id":"357-20014036","name":"SINAR MUTIARA HARAPAN","roles":["tenderer"]},{"id":"357-20021943","name":"SINAR SETIA TRADING","roles":["tenderer"]},{"id":"357-20026554","name":"BUMITRA","roles":["tenderer"]},{"id":"357-2000034017","name":"DHUHA ENTERPRISE","roles":["tenderer"]},{"id":"357-20031356","name":"EXCELLENT LOGISTICS","roles":["tenderer"]},{"id":"357-20004939","name":"WIRA WARIS ENTERPRISE","roles":["tenderer"]},{"id":"357-20030758","name":"IRPAN ENTERPRISE","roles":["tenderer"]},{"id":"357-20031170","name":"BURUJ ENTERPRISE","roles":["tenderer"]},{"id":"357-02039866","name":"EL-SPACE CORPORATION","roles":["tenderer"]},{"id":"146","name":"KEMENTERIAN DALAM NEGERI","roles":["buyer"]},{"id":"53","name":"POLIS DIRAJA MALAYSIA","roles":["procuringEntity"]}],"buyer":{"id":"53","name":"POLIS DIRAJA MALAYSIA"},"tender":{"id":"ocds-vesric-2IN6-20190719154440-QT190000000034859-tender","title":"PERKHIDMATAN PENYELENGGARAAN BERKALA SISTEM PEMBENTUNGAN \/ KUMBAHAN KOMPLEKS IBU PEJABAT POLIS DAERAH, BALAI POLIS DAN PONDOK POLIS DAERAH KOTA KINABALU, SABAH","status":"complete","procurementMethod":"limited","tenderPeriod":{"startDate":"2019-07-19T15:44:40+08:00","endDate":"2019-07-19T15:44:40+08:00"},"numberOfTenderers":13,"tenderers":[{"id":"357-20025389","name":"BINTAFA HOLDING"},{"id":"357-20020890","name":"EMMA PUNCAK JAYA ENTERPRISE"},{"id":"357-20031897","name":"ZAIKON MEWAH ENTERPRISE"},{"id":"357-20031079","name":"G. GENERATION AGENCY"},{"id":"357-20014036","name":"SINAR MUTIARA HARAPAN"},{"id":"357-20021943","name":"SINAR SETIA TRADING"},{"id":"357-20026554","name":"BUMITRA"},{"id":"357-2000034017","name":"DHUHA ENTERPRISE"},{"id":"357-20031356","name":"EXCELLENT LOGISTICS"},{"id":"357-20004939","name":"WIRA WARIS ENTERPRISE"},{"id":"357-20030758","name":"IRPAN ENTERPRISE"},{"id":"357-20031170","name":"BURUJ ENTERPRISE"},{"id":"357-02039866","name":"EL-SPACE CORPORATION"}]},"awards":[{"id":"ocds-vesric-2IN6-20190719154440-QT190000000034859-award","title":"PERKHIDMATAN PENYELENGGARAAN BERKALA SISTEM PEMBENTUNGAN \/ KUMBAHAN KOMPLEKS IBU PEJABAT POLIS DAERAH, BALAI POLIS DAN PONDOK POLIS DAERAH KOTA KINABALU, SABAH","status":"active","value":{"amount":"201440.00","currency":"MYR"},"suppliers":[{"id":"357-20025389","name":"BINTAFA HOLDING"}]}]}