{"ocid":"ocds-vesric-ZBJ3-20190719160036","id":"ocds-vesric-ZBJ3-20190719160036-QT190000000042641","date":"2019-07-19T16:00:36+08:00","language":"ms","tag":["tender","award"],"initiationType":"tender","parties":[{"id":"357-20027374","name":"BERANI BERJAYA","roles":["tenderer"]},{"id":"357-02041852","name":"SYARIKAT ZAI & NOOR ENTERPRISE","roles":["tenderer"]},{"id":"357-20013959","name":"NOR ENTERPRISE","roles":["tenderer"]},{"id":"357-20025326","name":"A & A ENTERPRISE","roles":["tenderer"]},{"id":"357-20031794","name":"R.A TRADING","roles":["tenderer"]},{"id":"357-20025690","name":"M.S CONSTRUCTION AND ENGINEERING CONSORTIUM","roles":["tenderer","supplier"]},{"id":"357-2000034005","name":"IMAN INTEGRATED RESOURCES","roles":["tenderer"]},{"id":"357-2000034350","name":"MEZA MARKETING","roles":["tenderer"]},{"id":"357-20027374","name":"BERANI BERJAYA","roles":["tenderer"]},{"id":"357-02041852","name":"SYARIKAT ZAI & NOOR ENTERPRISE","roles":["tenderer"]},{"id":"357-20013959","name":"NOR ENTERPRISE","roles":["tenderer"]},{"id":"357-20025326","name":"A & A ENTERPRISE","roles":["tenderer"]},{"id":"357-20031794","name":"R.A TRADING","roles":["tenderer"]},{"id":"357-20025690","name":"M.S CONSTRUCTION AND ENGINEERING CONSORTIUM","roles":["tenderer","supplier"]},{"id":"357-2000034005","name":"IMAN INTEGRATED RESOURCES","roles":["tenderer"]},{"id":"357-2000034350","name":"MEZA MARKETING","roles":["tenderer"]},{"id":"123","name":"KEMENTERIAN KESIHATAN","roles":["buyer"]},{"id":"42","name":"KUMPULAN PTJ KEMENTERIAN KESIHATAN","roles":["procuringEntity"]}],"buyer":{"id":"42","name":"KUMPULAN PTJ KEMENTERIAN KESIHATAN"},"tender":{"id":"ocds-vesric-ZBJ3-20190719160036-QT190000000042641-tender","title":"SEBUT HARGA MEMBEKAL DAN MENGHANTAR BAHAN MAKANAN BASAH DAN KERING KE HOSPITAL TAWAU, SABAH BAGI TEMPOH TIGA (3) BULAN","status":"complete","procurementMethod":"limited","tenderPeriod":{"startDate":"2019-07-19T16:00:36+08:00","endDate":"2019-07-19T16:00:36+08:00"},"numberOfTenderers":16,"tenderers":[{"id":"357-20027374","name":"BERANI BERJAYA"},{"id":"357-02041852","name":"SYARIKAT ZAI & NOOR ENTERPRISE"},{"id":"357-20013959","name":"NOR ENTERPRISE"},{"id":"357-20025326","name":"A & A ENTERPRISE"},{"id":"357-20031794","name":"R.A TRADING"},{"id":"357-20025690","name":"M.S CONSTRUCTION AND ENGINEERING CONSORTIUM"},{"id":"357-2000034005","name":"IMAN INTEGRATED RESOURCES"},{"id":"357-2000034350","name":"MEZA MARKETING"},{"id":"357-20027374","name":"BERANI BERJAYA"},{"id":"357-02041852","name":"SYARIKAT ZAI & NOOR ENTERPRISE"},{"id":"357-20013959","name":"NOR ENTERPRISE"},{"id":"357-20025326","name":"A & A ENTERPRISE"},{"id":"357-20031794","name":"R.A TRADING"},{"id":"357-20025690","name":"M.S CONSTRUCTION AND ENGINEERING CONSORTIUM"},{"id":"357-2000034005","name":"IMAN INTEGRATED RESOURCES"},{"id":"357-2000034350","name":"MEZA MARKETING"}]},"awards":[{"id":"ocds-vesric-ZBJ3-20190719160036-QT190000000042641-award","title":"SEBUT HARGA MEMBEKAL DAN MENGHANTAR BAHAN MAKANAN BASAH DAN KERING KE HOSPITAL TAWAU, SABAH BAGI TEMPOH TIGA (3) BULAN","status":"active","value":{"amount":"499839.00","currency":"MYR"},"suppliers":[{"id":"357-20025690","name":"M.S CONSTRUCTION AND ENGINEERING CONSORTIUM"}]}]}