{"uri":"https:\/\/cartelogy.data.gov.my\/ocds\/2019\/ocds-vesric-T2FP-20190719155242.json","version":"1.1","publishedDate":"2019-07-19T15:52:42+08:00","releases":[{"ocid":"ocds-vesric-T2FP-20190719155242","id":"ocds-vesric-T2FP-20190719155242-QT190000000031230","date":"2019-07-19T15:52:42+08:00","language":"ms","tag":["tender","award"],"initiationType":"tender","parties":[{"id":"357-00048443","name":"JATI WIRA KAWALAN SDN BHD","roles":["tenderer"]},{"id":"357-02068965","name":"PERISAI BERNAS (M) SDN. BHD.","roles":["tenderer"]},{"id":"357-02221402","name":"ANGKASA MAJU SECURITY SDN BHD","roles":["tenderer"]},{"id":"357-00037572","name":"KAWALAN KESELAMATAN BG SDN. BHD.","roles":["tenderer"]},{"id":"357-00050367","name":"AURA SECURITY SERVICES SDN BHD","roles":["tenderer"]},{"id":"357-02229765","name":"WARISAN PERKASA SECURITY SDN BHD","roles":["tenderer"]},{"id":"357-02059790","name":"ZB SECURITY SERVICES SDN. BHD.","roles":["tenderer"]},{"id":"357-00009820","name":"AWARA SECURITY SERVICES (M) SDN. BHD.","roles":["tenderer"]},{"id":"357-00028240","name":"KRIS KAWALRAPI SDN BHD","roles":["tenderer"]},{"id":"357-02001084","name":"FULLFORCE SECURITY SERVICES SDN BHD","roles":["tenderer"]},{"id":"357-02134357","name":"EXPERT SECURITY SERVICES SDN. BHD.","roles":["tenderer"]},{"id":"357-02242093","name":"IRIS INTELLIGENCE ALLIED SDN BHD","roles":["tenderer"]},{"id":"357-00037448","name":"INDAH SECURITY SERVICES SDN. BHD.","roles":["tenderer","supplier"]},{"id":"357-02233812","name":"SHARK FORCE SDN BHD","roles":["tenderer"]},{"id":"357-00040341","name":"WINNING FORCE SECURITY SERVICES SDN. BHD.","roles":["tenderer"]},{"id":"357-02180948","name":"SEAGULL FORCE SDN BHD","roles":["tenderer"]},{"id":"357-02132479","name":"KANI SECURITY SERVICES SDN. BHD.","roles":["tenderer"]},{"id":"357-02018259","name":"PERKASAFORCE SDN.BHD","roles":["tenderer"]},{"id":"357-02102754","name":"BB KAWALAN SDN. BHD.","roles":["tenderer"]},{"id":"357-02145076","name":"GLOBAL FORCE SECURITY SDN BHD","roles":["tenderer"]},{"id":"357-02056485","name":"KAWEKAWA SECURITY (M) SDN BHD","roles":["tenderer"]},{"id":"357-02241610","name":"GERBANG KAWALAN SDN. BHD.","roles":["tenderer"]},{"id":"357-02231379","name":"SYMPHONY GUARDFORCE SDN BHD","roles":["tenderer"]},{"id":"357-02204407","name":"DYNAMIC GUARDFORCE SDN BHD","roles":["tenderer"]},{"id":"357-01002749","name":"SEJAHTERA SECURITY SDN BHD","roles":["tenderer"]},{"id":"141","name":"KEMENTERIAN AIR, TANAH DAN SUMBER ASLI","roles":["buyer"]},{"id":"32","name":"KUMPULAN PTJ KEMENTERIAN SUMBER ASLI DAN ALAM SEKITAR","roles":["procuringEntity"]}],"buyer":{"id":"32","name":"KUMPULAN PTJ KEMENTERIAN SUMBER ASLI DAN ALAM SEKITAR"},"tender":{"id":"ocds-vesric-T2FP-20190719155242-QT190000000031230-tender","title":"PERKHIDMATAN KAWALAN KESELAMATAN DI JABATAN PERHILITAN NEGERI PERLIS","status":"complete","procurementMethod":"limited","tenderPeriod":{"startDate":"2019-07-19T15:52:42+08:00","endDate":"2019-07-19T15:52:42+08:00"},"numberOfTenderers":25,"tenderers":[{"id":"357-00048443","name":"JATI WIRA KAWALAN SDN BHD"},{"id":"357-02068965","name":"PERISAI BERNAS (M) SDN. BHD."},{"id":"357-02221402","name":"ANGKASA MAJU SECURITY SDN BHD"},{"id":"357-00037572","name":"KAWALAN KESELAMATAN BG SDN. BHD."},{"id":"357-00050367","name":"AURA SECURITY SERVICES SDN BHD"},{"id":"357-02229765","name":"WARISAN PERKASA SECURITY SDN BHD"},{"id":"357-02059790","name":"ZB SECURITY SERVICES SDN. BHD."},{"id":"357-00009820","name":"AWARA SECURITY SERVICES (M) SDN. BHD."},{"id":"357-00028240","name":"KRIS KAWALRAPI SDN BHD"},{"id":"357-02001084","name":"FULLFORCE SECURITY SERVICES SDN BHD"},{"id":"357-02134357","name":"EXPERT SECURITY SERVICES SDN. BHD."},{"id":"357-02242093","name":"IRIS INTELLIGENCE ALLIED SDN BHD"},{"id":"357-00037448","name":"INDAH SECURITY SERVICES SDN. BHD."},{"id":"357-02233812","name":"SHARK FORCE SDN BHD"},{"id":"357-00040341","name":"WINNING FORCE SECURITY SERVICES SDN. BHD."},{"id":"357-02180948","name":"SEAGULL FORCE SDN BHD"},{"id":"357-02132479","name":"KANI SECURITY SERVICES SDN. BHD."},{"id":"357-02018259","name":"PERKASAFORCE SDN.BHD"},{"id":"357-02102754","name":"BB KAWALAN SDN. BHD."},{"id":"357-02145076","name":"GLOBAL FORCE SECURITY SDN BHD"},{"id":"357-02056485","name":"KAWEKAWA SECURITY (M) SDN BHD"},{"id":"357-02241610","name":"GERBANG KAWALAN SDN. BHD."},{"id":"357-02231379","name":"SYMPHONY GUARDFORCE SDN BHD"},{"id":"357-02204407","name":"DYNAMIC GUARDFORCE SDN BHD"},{"id":"357-01002749","name":"SEJAHTERA SECURITY SDN BHD"}]},"awards":[{"id":"ocds-vesric-T2FP-20190719155242-QT190000000031230-award","title":"PERKHIDMATAN KAWALAN KESELAMATAN DI JABATAN PERHILITAN NEGERI PERLIS","status":"active","value":{"amount":"44573.76","currency":"MYR"},"suppliers":[{"id":"357-00037448","name":"INDAH SECURITY SERVICES SDN. BHD."}]}]}],"publisher":{"name":"MALAYSIAN ADMINISTRATIVE MODERNISATION AND MANAGEMENT PLANNING UNIT","uri":"https:\/\/www.mampu.gov.my"}}