{"uri":"http:\/\/cartelogy-backend.test\/published\/ocds\/ocds-vesric-79XIYKMK-20190720150342.json","version":"1.1","publishedDate":"2019-07-20T15:03:42+08:00","releases":[{"ocid":"ocds-vesric-79XIYKMK-20190720150342","id":"ocds-vesric-79XIYKMK-20190720150342-QT190000000034648","date":"2019-07-20T15:03:42+08:00","language":"ms","tag":["tender","award"],"initiationType":"tender","parties":[{"id":"357-00011054","name":"MUTIARA MURNI SDN BHD","roles":["tenderer"]},{"id":"357-00043583","name":"SEREMBAN PREMIER PHARMACY SDN BHD","roles":["tenderer","supplier"]},{"id":"357-01012215","name":"PHARMASERV ALLIANCES SDN BHD","roles":["tenderer"]},{"id":"123","name":"KEMENTERIAN KESIHATAN","roles":["buyer"]},{"id":"42","name":"KUMPULAN PTJ KEMENTERIAN KESIHATAN","roles":["procuringEntity"]}],"buyer":{"id":"42","name":"KUMPULAN PTJ KEMENTERIAN KESIHATAN"},"tender":{"id":"ocds-vesric-79XIYKMK-20190720150342-QT190000000034648-tender","title":"SEBUTHARGA MEMBEKAL DAN MENGHANTAR CALCITRIOL 1MCG\/ML INJECTION BAGI KEGUNAAN HOSPITAL MELAKA, HOSPITAL ALOR GAJAH DAN HOSPITAL JASIN","status":"complete","procurementMethod":"limited","tenderPeriod":{"startDate":"2019-07-20T15:03:42+08:00","endDate":"2019-07-20T15:03:42+08:00"},"numberOfTenderers":3,"tenderers":[{"id":"357-00011054","name":"MUTIARA MURNI SDN BHD"},{"id":"357-00043583","name":"SEREMBAN PREMIER PHARMACY SDN BHD"},{"id":"357-01012215","name":"PHARMASERV ALLIANCES SDN BHD"}]},"awards":[{"id":"ocds-vesric-79XIYKMK-20190720150342-QT190000000034648-award","title":"SEBUTHARGA MEMBEKAL DAN MENGHANTAR CALCITRIOL 1MCG\/ML INJECTION BAGI KEGUNAAN HOSPITAL MELAKA, HOSPITAL ALOR GAJAH DAN HOSPITAL JASIN","status":"active","value":{"amount":"474720.00","currency":"MYR"},"suppliers":[{"id":"357-00043583","name":"SEREMBAN PREMIER PHARMACY SDN BHD"}]}]}],"publisher":{"name":"MALAYSIAN ADMINISTRATIVE MODERNISATION AND MANAGEMENT PLANNING UNIT","uri":"https:\/\/www.mampu.gov.my"}}