{"uri":"http:\/\/cartelogy-backend.test\/published\/ocds\/ocds-vesric-HW6FW4TS-20190720150626.json","version":"1.1","publishedDate":"2019-07-20T15:06:26+08:00","releases":[{"ocid":"ocds-vesric-HW6FW4TS-20190720150626","id":"ocds-vesric-HW6FW4TS-20190720150626-QT190000000035933","date":"2019-07-20T15:06:26+08:00","language":"ms","tag":["tender","award"],"initiationType":"tender","parties":[{"id":"357-30013713","name":"WIJA PHARMA SDN BHD","roles":["tenderer","supplier"]},{"id":"357-30021626","name":"CAHAYA MEKAR JAYA SDN BHD","roles":["tenderer"]},{"id":"123","name":"KEMENTERIAN KESIHATAN","roles":["buyer"]},{"id":"42","name":"KUMPULAN PTJ KEMENTERIAN KESIHATAN","roles":["procuringEntity"]}],"buyer":{"id":"42","name":"KUMPULAN PTJ KEMENTERIAN KESIHATAN"},"tender":{"id":"ocds-vesric-HW6FW4TS-20190720150626-QT190000000035933-tender","title":"MEMBEKAL DAN MENGHANTAR UBAT HYPROMELLOSE 0.3% + CARBOMER 980 OPTHALMIC GEL KE UNIT FARMASI LOGISTIK, JABATAN FARMASI, HOSPITAL UMUM SARAWAK (18\/SF\/191) PS","status":"complete","procurementMethod":"limited","tenderPeriod":{"startDate":"2019-07-20T15:06:26+08:00","endDate":"2019-07-20T15:06:26+08:00"},"numberOfTenderers":2,"tenderers":[{"id":"357-30013713","name":"WIJA PHARMA SDN BHD"},{"id":"357-30021626","name":"CAHAYA MEKAR JAYA SDN BHD"}]},"awards":[{"id":"ocds-vesric-HW6FW4TS-20190720150626-QT190000000035933-award","title":"MEMBEKAL DAN MENGHANTAR UBAT HYPROMELLOSE 0.3% + CARBOMER 980 OPTHALMIC GEL KE UNIT FARMASI LOGISTIK, JABATAN FARMASI, HOSPITAL UMUM SARAWAK (18\/SF\/191) PS","status":"active","value":{"amount":"142200.00","currency":"MYR"},"suppliers":[{"id":"357-30013713","name":"WIJA PHARMA SDN BHD"}]}]}],"publisher":{"name":"MALAYSIAN ADMINISTRATIVE MODERNISATION AND MANAGEMENT PLANNING UNIT","uri":"https:\/\/www.mampu.gov.my"}}