{"uri":"http:\/\/cartelogy-backend.test\/published\/ocds\/ocds-vesric-0X8NN2FQ-20190720150949.json","version":"1.1","publishedDate":"2019-07-20T15:09:49+08:00","releases":[{"ocid":"ocds-vesric-0X8NN2FQ-20190720150949","id":"ocds-vesric-0X8NN2FQ-20190720150949-QT190000000033958","date":"2019-07-20T15:09:49+08:00","language":"ms","tag":["tender","award"],"initiationType":"tender","parties":[{"id":"357-02085064","name":"NEURON DYNAMICS ENTERPRISE","roles":["tenderer","supplier"]},{"id":"357-02156079","name":"RENCOM VISION VENTURES","roles":["tenderer"]},{"id":"114","name":"KEMENTERIAN SUMBER MANUSIA","roles":["buyer"]},{"id":"47","name":"KUMPULAN PTJ KEMENTERIAN SUMBER MANUSIA","roles":["procuringEntity"]}],"buyer":{"id":"47","name":"KUMPULAN PTJ KEMENTERIAN SUMBER MANUSIA"},"tender":{"id":"ocds-vesric-0X8NN2FQ-20190720150949-QT190000000033958-tender","title":"SEBUTHARGA BAGI PERKHIDMATAN PENYELENGGARAAN DAN MENGUJIGUNA PERALATAN LATIHAN JABATAN MEKANIKAL PEMBUATAN DAN BAHAGIAN MEKATRONIK DI PUSAT LATIHAN TEKNOLOGI TINGGI (ADTEC) KULIM, KEDAH BAGI TAHUN 2019","status":"complete","procurementMethod":"limited","tenderPeriod":{"startDate":"2019-07-20T15:09:49+08:00","endDate":"2019-07-20T15:09:49+08:00"},"numberOfTenderers":2,"tenderers":[{"id":"357-02085064","name":"NEURON DYNAMICS ENTERPRISE"},{"id":"357-02156079","name":"RENCOM VISION VENTURES"}]},"awards":[{"id":"ocds-vesric-0X8NN2FQ-20190720150949-QT190000000033958-award","title":"SEBUTHARGA BAGI PERKHIDMATAN PENYELENGGARAAN DAN MENGUJIGUNA PERALATAN LATIHAN JABATAN MEKANIKAL PEMBUATAN DAN BAHAGIAN MEKATRONIK DI PUSAT LATIHAN TEKNOLOGI TINGGI (ADTEC) KULIM, KEDAH BAGI TAHUN 2019","status":"active","value":{"amount":"80000.00","currency":"MYR"},"suppliers":[{"id":"357-02085064","name":"NEURON DYNAMICS ENTERPRISE"}]}]}],"publisher":{"name":"MALAYSIAN ADMINISTRATIVE MODERNISATION AND MANAGEMENT PLANNING UNIT","uri":"https:\/\/www.mampu.gov.my"}}