{"uri":"http:\/\/cartelogy-backend.test\/published\/ocds\/ocds-vesric-BS01BJ5M-20190720150643.json","version":"1.1","publishedDate":"2019-07-20T15:06:43+08:00","releases":[{"ocid":"ocds-vesric-BS01BJ5M-20190720150643","id":"ocds-vesric-BS01BJ5M-20190720150643-QT190000000032923","date":"2019-07-20T15:06:43+08:00","language":"ms","tag":["tender","award"],"initiationType":"tender","parties":[{"id":"357-00012212","name":"GELIGA SISTEM SDN BHD","roles":["tenderer"]},{"id":"357-02263458","name":"J & J MURNI SDN BHD","roles":["tenderer","supplier"]},{"id":"357-02010266","name":"UTAS MAJU SDN BHD","roles":["tenderer"]},{"id":"123","name":"KEMENTERIAN KESIHATAN","roles":["buyer"]},{"id":"42","name":"KUMPULAN PTJ KEMENTERIAN KESIHATAN","roles":["procuringEntity"]}],"buyer":{"id":"42","name":"KUMPULAN PTJ KEMENTERIAN KESIHATAN"},"tender":{"id":"ocds-vesric-BS01BJ5M-20190720150643-QT190000000032923-tender","title":"SEBUT HARGA MEMBEKAL DAN MENGHANTAR BEKALAN REAGENT DAN PERALATAN (AUTOMATED COAGULATION ANALYSER) \"REAGENT RENTAL\" BAGI TEMPOH 2 TAHUN UNTUK UJIAN KOAGULASI KE KK TAIPING","status":"complete","procurementMethod":"limited","tenderPeriod":{"startDate":"2019-07-20T15:06:43+08:00","endDate":"2019-07-20T15:06:43+08:00"},"numberOfTenderers":3,"tenderers":[{"id":"357-00012212","name":"GELIGA SISTEM SDN BHD"},{"id":"357-02263458","name":"J & J MURNI SDN BHD"},{"id":"357-02010266","name":"UTAS MAJU SDN BHD"}]},"awards":[{"id":"ocds-vesric-BS01BJ5M-20190720150643-QT190000000032923-award","title":"SEBUT HARGA MEMBEKAL DAN MENGHANTAR BEKALAN REAGENT DAN PERALATAN (AUTOMATED COAGULATION ANALYSER) \"REAGENT RENTAL\" BAGI TEMPOH 2 TAHUN UNTUK UJIAN KOAGULASI KE KK TAIPING","status":"active","value":{"amount":"128482.06","currency":"MYR"},"suppliers":[{"id":"357-02263458","name":"J & J MURNI SDN BHD"}]}]}],"publisher":{"name":"MALAYSIAN ADMINISTRATIVE MODERNISATION AND MANAGEMENT PLANNING UNIT","uri":"https:\/\/www.mampu.gov.my"}}