{"uri":"http:\/\/cartelogy-backend.test\/published\/ocds\/ocds-vesric-BN6RH8YF-20190720145235.json","version":"1.1","publishedDate":"2019-07-20T14:52:35+08:00","releases":[{"ocid":"ocds-vesric-BN6RH8YF-20190720145235","id":"ocds-vesric-BN6RH8YF-20190720145235-QT190000000040482","date":"2019-07-20T14:52:35+08:00","language":"ms","tag":["tender","award"],"initiationType":"tender","parties":[{"id":"357-02258045","name":"ANF GLOBAL RESOURCES","roles":["tenderer"]},{"id":"357-02055009","name":"EITA ELEVATOR (M) SDN BHD","roles":["tenderer"]},{"id":"357-02268045","name":"ASIA FUJI ELEVATOR SDN. BHD.","roles":["tenderer","supplier"]},{"id":"139","name":"KEMENTERIAN TENAGA, SAINS, TEKNOLOGI, ALAM SEKITAR DAN PERUBAHAN IKLIM","roles":["buyer"]},{"id":"38","name":"KUMPULAN PTJ KEMENTERIAN TENAGA, SAINS, TEKNOLOGI ALAM SEKITAR DAN PERUBAHAN IKLIM","roles":["procuringEntity"]}],"buyer":{"id":"38","name":"KUMPULAN PTJ KEMENTERIAN TENAGA, SAINS, TEKNOLOGI ALAM SEKITAR DAN PERUBAHAN IKLIM"},"tender":{"id":"ocds-vesric-BN6RH8YF-20190720145235-QT190000000040482-tender","title":"PERKHIDMATAN PENYENGGARAAN  BULANAN DUA (2) UNIT LIF PENUMPANG SECARA NON COMPREHENSIF  DI IBU PEJABAT LEMBAGA PERLESENAN TENAGA ATOM BAGI TEMPOH DUA (2) TAHUN ","status":"complete","procurementMethod":"limited","tenderPeriod":{"startDate":"2019-07-20T14:52:35+08:00","endDate":"2019-07-20T14:52:35+08:00"},"numberOfTenderers":3,"tenderers":[{"id":"357-02258045","name":"ANF GLOBAL RESOURCES"},{"id":"357-02055009","name":"EITA ELEVATOR (M) SDN BHD"},{"id":"357-02268045","name":"ASIA FUJI ELEVATOR SDN. BHD."}]},"awards":[{"id":"ocds-vesric-BN6RH8YF-20190720145235-QT190000000040482-award","title":"PERKHIDMATAN PENYENGGARAAN  BULANAN DUA (2) UNIT LIF PENUMPANG SECARA NON COMPREHENSIF  DI IBU PEJABAT LEMBAGA PERLESENAN TENAGA ATOM BAGI TEMPOH DUA (2) TAHUN ","status":"active","value":{"amount":"27840.00","currency":"MYR"},"suppliers":[{"id":"357-02268045","name":"ASIA FUJI ELEVATOR SDN. BHD."}]}]}],"publisher":{"name":"MALAYSIAN ADMINISTRATIVE MODERNISATION AND MANAGEMENT PLANNING UNIT","uri":"https:\/\/www.mampu.gov.my"}}