{"uri":"http:\/\/cartelogy-backend.test\/published\/ocds\/ocds-vesric-XSJNIG5I-20190720145622.json","version":"1.1","publishedDate":"2019-07-20T14:56:22+08:00","releases":[{"ocid":"ocds-vesric-XSJNIG5I-20190720145622","id":"ocds-vesric-XSJNIG5I-20190720145622-QT190000000035575","date":"2019-07-20T14:56:22+08:00","language":"ms","tag":["tender","award"],"initiationType":"tender","parties":[{"id":"357-02232657","name":"MITRA BAYU RESOURCES","roles":["tenderer"]},{"id":"357-02200318","name":"GEO BILD (M) SDN. BHD.","roles":["tenderer"]},{"id":"357-01004326","name":"JRC-PRO TECHNOLOGY SDN BHD","roles":["tenderer"]},{"id":"357-02280855","name":"NUSA ENERGI IT SDN BHD","roles":["tenderer"]},{"id":"357-02179039","name":"MEGAH BERJAYA TRADING & SERVICES","roles":["tenderer"]},{"id":"357-01013325","name":"GOLDEN CONCRETE CONSTRUCTION & ENGINEERING","roles":["tenderer"]},{"id":"357-01000194","name":"JAYA ABADI BERSATU ENTERPRISE","roles":["tenderer"]},{"id":"357-02015598","name":"BURHANI STATIONERS","roles":["tenderer"]},{"id":"357-02114238","name":"ARENA STABIL SDN. BHD","roles":["tenderer"]},{"id":"357-02081708","name":"SUNDATA SDN. BHD.","roles":["tenderer"]},{"id":"357-02149745","name":"PERNIAGAAN SINAR SURIA SDN BHD","roles":["tenderer"]},{"id":"357-02137669","name":"MICRO VENTURE (M) SDN BHD","roles":["tenderer"]},{"id":"357-02048204","name":"ALGOMINDA SDN BHD","roles":["tenderer"]},{"id":"357-02056866","name":"NOVAMI HOLDINGS SDN BHD","roles":["tenderer"]},{"id":"357-01008605","name":"NL LOGISTICS SDN. BHD.","roles":["tenderer"]},{"id":"357-02056225","name":"REWANAS SDN. BHD.","roles":["tenderer"]},{"id":"357-02197739","name":"EL EMIIR RESOURCES","roles":["tenderer"]},{"id":"357-0002292613","name":"ELANG WAH SDN. BHD.","roles":["tenderer"]},{"id":"357-01004407","name":"SYAMADDUN SDN BHD","roles":["tenderer","supplier"]},{"id":"101","name":"JABATAN PERDANA MENTERI","roles":["buyer"]},{"id":"21","name":"KUMPULAN PTJ JABATAN PERDANA MENTERI","roles":["procuringEntity"]}],"buyer":{"id":"21","name":"KUMPULAN PTJ JABATAN PERDANA MENTERI"},"tender":{"id":"ocds-vesric-XSJNIG5I-20190720145622-QT190000000035575-tender","title":"PEMBEKALAN DAN PENGHANTARAN TONER MESIN PENCETAK UNTUK KEGUNAAN BAHAGIAN HAL EHWAL UNDANG-UNDANG, JABATAN PERDANA MENTERI","status":"complete","procurementMethod":"limited","tenderPeriod":{"startDate":"2019-07-20T14:56:22+08:00","endDate":"2019-07-20T14:56:22+08:00"},"numberOfTenderers":19,"tenderers":[{"id":"357-02232657","name":"MITRA BAYU RESOURCES"},{"id":"357-02200318","name":"GEO BILD (M) SDN. BHD."},{"id":"357-01004326","name":"JRC-PRO TECHNOLOGY SDN BHD"},{"id":"357-02280855","name":"NUSA ENERGI IT SDN BHD"},{"id":"357-02179039","name":"MEGAH BERJAYA TRADING & SERVICES"},{"id":"357-01013325","name":"GOLDEN CONCRETE CONSTRUCTION & ENGINEERING"},{"id":"357-01000194","name":"JAYA ABADI BERSATU ENTERPRISE"},{"id":"357-02015598","name":"BURHANI STATIONERS"},{"id":"357-02114238","name":"ARENA STABIL SDN. BHD"},{"id":"357-02081708","name":"SUNDATA SDN. BHD."},{"id":"357-02149745","name":"PERNIAGAAN SINAR SURIA SDN BHD"},{"id":"357-02137669","name":"MICRO VENTURE (M) SDN BHD"},{"id":"357-02048204","name":"ALGOMINDA SDN BHD"},{"id":"357-02056866","name":"NOVAMI HOLDINGS SDN BHD"},{"id":"357-01008605","name":"NL LOGISTICS SDN. BHD."},{"id":"357-02056225","name":"REWANAS SDN. BHD."},{"id":"357-02197739","name":"EL EMIIR RESOURCES"},{"id":"357-0002292613","name":"ELANG WAH SDN. BHD."},{"id":"357-01004407","name":"SYAMADDUN SDN BHD"}]},"awards":[{"id":"ocds-vesric-XSJNIG5I-20190720145622-QT190000000035575-award","title":"PEMBEKALAN DAN PENGHANTARAN TONER MESIN PENCETAK UNTUK KEGUNAAN BAHAGIAN HAL EHWAL UNDANG-UNDANG, JABATAN PERDANA MENTERI","status":"active","value":{"amount":"46155.30","currency":"MYR"},"suppliers":[{"id":"357-01004407","name":"SYAMADDUN SDN BHD"}]}]}],"publisher":{"name":"MALAYSIAN ADMINISTRATIVE MODERNISATION AND MANAGEMENT PLANNING UNIT","uri":"https:\/\/www.mampu.gov.my"}}